agentshield/__init__.py
agentshield/client.py
agentshield/exceptions.py
agentshield/interceptor.py
agentshield-0.1.1.dist-info/licenses/LICENSE
agentshield-0.1.1.dist-info/METADATA
agentshield-0.1.1.dist-info/WHEEL
agentshield-0.1.1.dist-info/top_level.txt
agentshield-0.1.1.dist-info/RECORD
