Metadata-Version: 2.4
Name: agentshield
Version: 0.1.1
Summary: Security and monitoring for AI agents
Home-page: https://agent-shield.com
Author: AgentShield
Author-email: AgentShield <support@agent-shield.com>
License: MIT
Project-URL: Homepage, https://agent-shield.com
Project-URL: Documentation, https://agent-shield.com/docs
Project-URL: Repository, https://github.com/agentshield/python-sdk
Project-URL: Bug Tracker, https://github.com/agentshield/python-sdk/issues
Keywords: ai,agent,security,monitoring,llm,safety
Classifier: Development Status :: 4 - Beta
Classifier: Intended Audience :: Developers
Classifier: License :: OSI Approved :: MIT License
Classifier: Programming Language :: Python :: 3
Classifier: Programming Language :: Python :: 3.8
Classifier: Programming Language :: Python :: 3.9
Classifier: Programming Language :: Python :: 3.10
Classifier: Programming Language :: Python :: 3.11
Classifier: Programming Language :: Python :: 3.12
Requires-Python: >=3.8
License-File: LICENSE
Requires-Dist: requests>=2.28.0
Requires-Dist: urllib3>=1.26.0
Provides-Extra: dev
Requires-Dist: pytest>=7.0.0; extra == "dev"
Requires-Dist: pytest-cov>=4.0.0; extra == "dev"
Requires-Dist: pytest-mock>=3.10.0; extra == "dev"
Requires-Dist: black>=22.0.0; extra == "dev"
Requires-Dist: flake8>=5.0.0; extra == "dev"
Requires-Dist: mypy>=0.990; extra == "dev"
Requires-Dist: types-requests>=2.28.0; extra == "dev"
Provides-Extra: langchain
Requires-Dist: langchain>=0.1.0; extra == "langchain"
Dynamic: author
Dynamic: home-page
Dynamic: license-file
Dynamic: requires-python
